{
	"info": {
		"_postman_id": "d8c128a4-fa00-4f00-9934-bae7be43940f",
		"name": "ENOCA PROJECT REQUESTS",
		"schema": "https://schema.getpostman.com/json/collection/v2.1.0/collection.json",
		"_exporter_id": "16557070"
	},
	"item": [
		{
			"name": "employee list",
			"request": {
				"method": "GET",
				"header": [],
				"url": {
					"raw": "http://localhost:8080/employee/list",
					"protocol": "http",
					"host": [
						"localhost"
					],
					"port": "8080",
					"path": [
						"employee",
						"list"
					]
				}
			},
			"response": []
		},
		{
			"name": "update employee",
			"request": {
				"method": "PUT",
				"header": [],
				"body": {
					"mode": "raw",
					"raw": "{\r\n    \"position\": \"Full Stack Engineer\"\r\n}",
					"options": {
						"raw": {
							"language": "json"
						}
					}
				},
				"url": {
					"raw": "http://localhost:8080/employee/5",
					"protocol": "http",
					"host": [
						"localhost"
					],
					"port": "8080",
					"path": [
						"employee",
						"5"
					]
				}
			},
			"response": []
		},
		{
			"name": "delete employee",
			"request": {
				"method": "DELETE",
				"header": [],
				"url": {
					"raw": "http://localhost:8080/employee/16",
					"protocol": "http",
					"host": [
						"localhost"
					],
					"port": "8080",
					"path": [
						"employee",
						"16"
					]
				}
			},
			"response": []
		},
		{
			"name": "get employee by id",
			"request": {
				"method": "GET",
				"header": [],
				"url": {
					"raw": "http://localhost:8080/employee/5",
					"protocol": "http",
					"host": [
						"localhost"
					],
					"port": "8080",
					"path": [
						"employee",
						"5"
					]
				}
			},
			"response": []
		},
		{
			"name": "save employee",
			"request": {
				"method": "POST",
				"header": [],
				"body": {
					"mode": "raw",
					"raw": "{\r\n    \"name\":\"Kelly Smith\",\r\n    \"position\":\"Backend Engineer\",\r\n    \"company\": {\r\n        \"id\":2\r\n    }\r\n}",
					"options": {
						"raw": {
							"language": "json"
						}
					}
				},
				"url": {
					"raw": "http://localhost:8080/employee",
					"protocol": "http",
					"host": [
						"localhost"
					],
					"port": "8080",
					"path": [
						"employee"
					]
				}
			},
			"response": []
		},
		{
			"name": "company save",
			"request": {
				"method": "POST",
				"header": [],
				"body": {
					"mode": "raw",
					"raw": "{\r\n    \"name\":\"ComAny\"\r\n}",
					"options": {
						"raw": {
							"language": "json"
						}
					}
				},
				"url": {
					"raw": "http://localhost:8080/company",
					"protocol": "http",
					"host": [
						"localhost"
					],
					"port": "8080",
					"path": [
						"company"
					]
				}
			},
			"response": []
		},
		{
			"name": "company list",
			"request": {
				"method": "GET",
				"header": [],
				"url": {
					"raw": "http://localhost:8080/company/list",
					"protocol": "http",
					"host": [
						"localhost"
					],
					"port": "8080",
					"path": [
						"company",
						"list"
					]
				}
			},
			"response": []
		},
		{
			"name": "get company by id",
			"request": {
				"method": "GET",
				"header": [],
				"url": {
					"raw": "http://localhost:8080/company/2",
					"protocol": "http",
					"host": [
						"localhost"
					],
					"port": "8080",
					"path": [
						"company",
						"2"
					]
				}
			},
			"response": []
		},
		{
			"name": "update company",
			"request": {
				"method": "PUT",
				"header": [],
				"body": {
					"mode": "raw",
					"raw": "{\r\n    \"name\":\"UpdateD\"\r\n}",
					"options": {
						"raw": {
							"language": "json"
						}
					}
				},
				"url": {
					"raw": "http://localhost:8080/company/2",
					"protocol": "http",
					"host": [
						"localhost"
					],
					"port": "8080",
					"path": [
						"company",
						"2"
					]
				}
			},
			"response": []
		},
		{
			"name": "get company employees",
			"request": {
				"method": "GET",
				"header": [],
				"url": {
					"raw": "http://localhost:8080/company/employee-list/2",
					"protocol": "http",
					"host": [
						"localhost"
					],
					"port": "8080",
					"path": [
						"company",
						"employee-list",
						"2"
					]
				}
			},
			"response": []
		},
		{
			"name": "delete company",
			"request": {
				"method": "DELETE",
				"header": [],
				"url": {
					"raw": "http://localhost:8080/company/6",
					"protocol": "http",
					"host": [
						"localhost"
					],
					"port": "8080",
					"path": [
						"company",
						"6"
					]
				}
			},
			"response": []
		}
	]
}